kinship_vis/__init__.py
kinship_vis/cli.py
kinship_vis/graph.py
kinship_vis/io.py
kinship_vis/viz.py
kinship_vis-0.1.2.dist-info/METADATA
kinship_vis-0.1.2.dist-info/WHEEL
kinship_vis-0.1.2.dist-info/entry_points.txt
kinship_vis-0.1.2.dist-info/licenses/LICENSE
kinship_vis-0.1.2.dist-info/RECORD
