Metadata-Version: 2.4
Name: kinship-vis
Version: 0.1.2
Summary: Kinship graph visualizer for PLINK .genome and KING .kin0 with PNG/TIFF and interactive HTML outputs
Project-URL: Homepage, https://github.com/alekseizarubin/kinship-vis
Project-URL: Issues, https://github.com/alekseizarubin/kinship-vis/issues
Project-URL: Repository, https://github.com/alekseizarubin/kinship-vis
Author-email: Aleksei Zarubin <a.a.zarubin@gmail.com>
License: MIT
License-File: LICENSE
Keywords: IBD,genomics,kinship,population genetics,visualization
Classifier: Intended Audience :: Science/Research
Classifier: License :: OSI Approved :: MIT License
Classifier: Operating System :: OS Independent
Classifier: Programming Language :: Python :: 3
Classifier: Programming Language :: Python :: 3 :: Only
Classifier: Programming Language :: Python :: 3.9
Classifier: Programming Language :: Python :: 3.10
Classifier: Programming Language :: Python :: 3.11
Classifier: Programming Language :: Python :: 3.12
Classifier: Programming Language :: Python :: 3.13
Classifier: Topic :: Scientific/Engineering :: Bio-Informatics
Requires-Python: >=3.9
Requires-Dist: matplotlib>=3.5
Requires-Dist: networkx>=3.0
Requires-Dist: numpy<2,>=1.23
Requires-Dist: pandas>=1.5
Requires-Dist: plotly<6,>=5
